<annotation>
	<folder>K</folder>
	<filename>K (13).jpg</filename>
	<path>D:\SIBI_datasets_LEMLITBANG\SIBI_datasets_LEMLITBANG_SIBI_R_90.10_RAW\SIBI_datasets_LEMLITBANG_SIBI_R_90.10_RAW\training\K\K (13).jpg</path>
	<source>
		<database>Unknown</database>
	</source>
	<size>
		<width>2000</width>
		<height>2000</height>
		<depth>3</depth>
	</size>
	<segmented>0</segmented>
	<object>
		<name>K</name>
		<pose>Unspecified</pose>
		<truncated>0</truncated>
		<difficult>0</difficult>
		<bndbox>
			<xmin>610</xmin>
			<ymin>158</ymin>
			<xmax>1532</xmax>
			<ymax>1815</ymax>
		</bndbox>
	</object>
</annotation>
